README.md
setup.py
py_clui/__init__.py
py_clui/colorize.py
py_clui.egg-info/PKG-INFO
py_clui.egg-info/SOURCES.txt
py_clui.egg-info/dependency_links.txt
py_clui.egg-info/top_level.txt