Metadata-Version: 2.1
Name: py-clui
Version: 0.0.3
Summary: Toolkit for quickly building nice looking command line interfaces
Home-page: https://github.com/hmleal/py-clui
Author: Henrique Leal
Author-email: hm.leal@hotmail.com
License: UNKNOWN
Platform: UNKNOWN
Classifier: Programming Language :: Python :: 3 :: Only
